Metadata-Version: 2.1
Name: gollama
Version: 1.1.0
Summary: Django implementation for golink
Home-page: https://github.com/sillyfatcat/gollama
Author: Shelby Shum
Author-email: sshum00@gmail.com
License: MIT
Download-URL: https://github.com/sillyfatcat/gollama/archive/v0.1.tar.gz
Keywords: golink,tinyurl,shorthand
Platform: UNKNOWN
Classifier: Development Status :: 5 - Production/Stable
Classifier: Intended Audience :: Developers
Classifier: Topic :: Internet :: Name Service (DNS)
Classifier: License :: OSI Approved :: MIT License
Classifier: Programming Language :: Python :: 3
Classifier: Programming Language :: Python :: 3.4
Classifier: Programming Language :: Python :: 3.5
Classifier: Programming Language :: Python :: 3.6
Classifier: Programming Language :: Python :: 3.7
Classifier: Programming Language :: Python :: 3.8
